odoo/addons/helpdesk_mgmt_stage_validation/README.rst
odoo/addons/helpdesk_mgmt_stage_validation/__init__.py
odoo/addons/helpdesk_mgmt_stage_validation/__manifest__.py
odoo/addons/helpdesk_mgmt_stage_validation/i18n/helpdesk_mgmt_stage_validation.pot
odoo/addons/helpdesk_mgmt_stage_validation/i18n/it.po
odoo/addons/helpdesk_mgmt_stage_validation/i18n/pt_BR.po
odoo/addons/helpdesk_mgmt_stage_validation/models/__init__.py
odoo/addons/helpdesk_mgmt_stage_validation/models/helpdesk_ticket.py
odoo/addons/helpdesk_mgmt_stage_validation/models/helpdesk_ticket_stage.py
odoo/addons/helpdesk_mgmt_stage_validation/readme/CONFIGURE.md
odoo/addons/helpdesk_mgmt_stage_validation/readme/CONTRIBUTORS.md
odoo/addons/helpdesk_mgmt_stage_validation/readme/DESCRIPTION.md
odoo/addons/helpdesk_mgmt_stage_validation/readme/USAGE.md
odoo/addons/helpdesk_mgmt_stage_validation/static/description/icon.png
odoo/addons/helpdesk_mgmt_stage_validation/static/description/index.html
odoo/addons/helpdesk_mgmt_stage_validation/tests/__init__.py
odoo/addons/helpdesk_mgmt_stage_validation/tests/test_helpdesk_ticket_stage_validation.py
odoo/addons/helpdesk_mgmt_stage_validation/views/helpdesk_ticket_stage.xml
odoo_addon_helpdesk_mgmt_stage_validation-18.0.1.0.0.3.dist-info/METADATA
odoo_addon_helpdesk_mgmt_stage_validation-18.0.1.0.0.3.dist-info/WHEEL
odoo_addon_helpdesk_mgmt_stage_validation-18.0.1.0.0.3.dist-info/top_level.txt
odoo_addon_helpdesk_mgmt_stage_validation-18.0.1.0.0.3.dist-info/RECORD
